ural/__init__.py
ural/__main__.py
ural/canonicalize_url.py
ural/canonicalize_url.pyi
ural/could_be_html.py
ural/could_be_html.pyi
ural/could_be_rss.py
ural/could_be_rss.pyi
ural/data.py
ural/ensure_protocol.py
ural/ensure_protocol.pyi
ural/exceptions.py
ural/facebook.py
ural/facebook.pyi
ural/fingerprint_url.py
ural/fingerprint_url.pyi
ural/force_protocol.py
ural/force_protocol.pyi
ural/format_url.py
ural/format_url.pyi
ural/get_hostname.py
ural/get_hostname.pyi
ural/google.py
ural/google.pyi
ural/has_special_host.py
ural/has_special_host.pyi
ural/infer_redirection.py
ural/infer_redirection.pyi
ural/instagram.py
ural/instagram.pyi
ural/is_homepage.py
ural/is_homepage.pyi
ural/is_shortened_url.py
ural/is_shortened_url.pyi
ural/is_typo_url.py
ural/is_typo_url.pyi
ural/is_url.py
ural/is_url.pyi
ural/links_from_html.py
ural/links_from_html.pyi
ural/normalize_url.py
ural/normalize_url.pyi
ural/patterns.py
ural/quote.py
ural/quote.pyi
ural/should_follow_href.py
ural/should_follow_href.pyi
ural/should_resolve.py
ural/should_resolve.pyi
ural/strip_protocol.py
ural/strip_protocol.pyi
ural/telegram.py
ural/telegram.pyi
ural/tld.py
ural/tld.pyi
ural/tld_data.py
ural/twitter.py
ural/twitter.pyi
ural/types.pyi
ural/urls_from_html.py
ural/urls_from_html.pyi
ural/urls_from_text.py
ural/urls_from_text.pyi
ural/utils.py
ural/utils.pyi
ural/youtube.py
ural/youtube.pyi
ural/classes/__init__.py
ural/classes/hostname_trie_set.py
ural/classes/hostname_trie_set.pyi
ural/classes/suffix_trie.py
ural/classes/suffix_trie.pyi
ural/classes/trie_dict.py
ural/classes/trie_dict.pyi
ural/lru/__init__.py
ural/lru/conversion.py
ural/lru/conversion.pyi
ural/lru/serialization.py
ural/lru/serialization.pyi
ural/lru/stems.py
ural/lru/stems.pyi
ural/lru/trie.py
ural/lru/trie.pyi
ural-1.5.0.dist-info/LICENSE.txt
ural-1.5.0.dist-info/METADATA
ural-1.5.0.dist-info/WHEEL
ural-1.5.0.dist-info/top_level.txt
ural-1.5.0.dist-info/zip-safe
ural-1.5.0.dist-info/RECORD
