Metadata-Version: 2.1
Name: ural
Version: 1.5.0
Summary: A helper library full of URL-related heuristics.
Home-page: http://github.com/medialab/ural
Author: Guillaume Plique, Jules Farjas, Oubine Perrin, Benjamin Ooghe-Tabanou, Martin Delabre, Pauline Breteau, Jean Descamps, Béatrice Mazoyer, Amélie Pellé, Laura Miguel, César Pichon
Author-email: guillaume.plique@sciencespo.fr
License: GPL-3.0
Keywords: url
Platform: UNKNOWN
Requires-Python: >=2.7
Requires-Dist: typing-extensions ; python_version<'3.8'
